pyninja/__init__.py
pyninja/cli.py
pyninja/main.py
pyninja_tool-1.0.0.dist-info/licenses/LICENSE
pyninja_tool-1.0.0.dist-info/METADATA
pyninja_tool-1.0.0.dist-info/WHEEL
pyninja_tool-1.0.0.dist-info/entry_points.txt
pyninja_tool-1.0.0.dist-info/top_level.txt
pyninja_tool-1.0.0.dist-info/RECORD
