Metadata-Version: 2.4
Name: pyninja-tool
Version: 1.0.0
Summary: 🥷 The ultimate Python dependency ninja - automate, secure, and modernize your requirements
Home-page: https://github.com/pyninja-dev/pyninja
Author: PyNinja Community
Author-email: community@pyninja.dev
Project-URL: Bug Tracker, https://github.com/pyninja-dev/pyninja/issues
Project-URL: Documentation, https://pyninja.dev/docs
Project-URL: Source Code, https://github.com/pyninja-dev/pyninja
Project-URL: Changelog, https://github.com/pyninja-dev/pyninja/releases
Keywords: dependencies,requirements,security,vulnerability,modernization,automation,python,pip,pypi,devops,ci-cd,ninja
Classifier: Development Status :: 5 - Production/Stable
Classifier: Intended Audience :: Developers
Classifier: Topic :: Software Development :: Libraries :: Python Modules
Classifier: Topic :: System :: Software Distribution
Classifier: Topic :: Security
Classifier: License :: OSI Approved :: MIT License
Classifier: Programming Language :: Python :: 3
Classifier: Programming Language :: Python :: 3.8
Classifier: Programming Language :: Python :: 3.9
Classifier: Programming Language :: Python :: 3.10
Classifier: Programming Language :: Python :: 3.11
Classifier: Programming Language :: Python :: 3.12
Classifier: Operating System :: OS Independent
Classifier: Environment :: Console
Classifier: Typing :: Typed
Requires-Python: >=3.8
License-File: LICENSE
Requires-Dist: packaging>=21.0
Requires-Dist: toml>=0.10.0
Requires-Dist: requests>=2.25.0
Requires-Dist: click>=8.0.0
Requires-Dist: rich>=12.0.0
Requires-Dist: aiohttp>=3.8.0
Provides-Extra: dev
Requires-Dist: pytest>=7.0.0; extra == "dev"
Requires-Dist: pytest-asyncio>=0.21.0; extra == "dev"
Requires-Dist: black>=22.0.0; extra == "dev"
Requires-Dist: isort>=5.10.0; extra == "dev"
Requires-Dist: mypy>=1.0.0; extra == "dev"
Requires-Dist: flake8>=4.0.0; extra == "dev"
Requires-Dist: pre-commit>=2.17.0; extra == "dev"
Provides-Extra: viz
Requires-Dist: graphviz>=0.20.0; extra == "viz"
Requires-Dist: matplotlib>=3.5.0; extra == "viz"
Provides-Extra: github
Requires-Dist: PyGithub>=1.55.0; extra == "github"
Requires-Dist: pygit2>=1.10.0; extra == "github"
Provides-Extra: all
Requires-Dist: graphviz>=0.20.0; extra == "all"
Requires-Dist: matplotlib>=3.5.0; extra == "all"
Requires-Dist: PyGithub>=1.55.0; extra == "all"
Requires-Dist: pygit2>=1.10.0; extra == "all"
Dynamic: author
Dynamic: author-email
Dynamic: classifier
Dynamic: description
Dynamic: description-content-type
Dynamic: home-page
Dynamic: keywords
Dynamic: license-file
Dynamic: project-url
Dynamic: provides-extra
Dynamic: requires-dist
Dynamic: requires-python
Dynamic: summary
